ambix/__init__.py
ambix/cli.py
ambix/commands/__init__.py
ambix/commands/flatten.py
ambix/commands/move.py
ambix/commands/prune.py
ambix/commands/rebase.py
ambix/commands/render.py
ambix/exceptions.py
ambix/migration_home.py
ambix/migration_script.py
ambix/utilities.py
ambix-1.0.0.dist-info/entry_points.txt
ambix-1.0.0.dist-info/LICENSE.md
ambix-1.0.0.dist-info/WHEEL
ambix-1.0.0.dist-info/METADATA
ambix-1.0.0.dist-info/RECORD
