Metadata-Version: 2.1
Name: ambix
Version: 1.0.0
Summary: alembic history cleaning tool
License: MIT
Author: Tucker Beck
Author-email: tucker.beck@gmail.com
Requires-Python: >=3.7,<4.0
Classifier: License :: OSI Approved :: MIT License
Classifier: Programming Language :: Python :: 3
Classifier: Programming Language :: Python :: 3.7
Classifier: Programming Language :: Python :: 3.8
Classifier: Programming Language :: Python :: 3.9
Requires-Dist: loguru (>=0.5.3,<0.6.0)
Requires-Dist: pendulum (>=2.1.2,<3.0.0)
Requires-Dist: py-buzz (>=2.1.3,<3.0.0)
Requires-Dist: redbaron (>=0.9.2,<0.10.0)
Requires-Dist: toposort (>=1.6,<2.0)
Requires-Dist: typer (>=0.3.2,<0.4.0)
